{
  "folder": "wG1rcu7WfQjp0t5T",
  "name": "Wild Surge",
  "type": "feature",
  "_id": "uQ6maTgZwUx54mau",
  "img": "modules/nimble-nimplus-content/assets/artwork/feature/award.png",
  "system": {
    "macro": "",
    "identifier": "",
    "rules": [],
    "activation": {
      "acquireTargetsFromTemplate": false,
      "cost": {
        "details": "",
        "quantity": 1,
        "type": "none",
        "isReaction": false
      },
      "duration": {
        "details": "",
        "quantity": 1,
        "type": "none"
      },
      "effects": [],
      "showDescription": true,
      "targets": {
        "count": 1,
        "restrictions": "",
        "attackType": "",
        "distance": 1
      },
      "template": {
        "length": 1,
        "radius": 1,
        "shape": "",
        "width": 1
      }
    },
    "description": "<p>(1/encounter) Ignore the Rushed Attacks penalty this turn. Recharges if your quarry crits you or an ally.</p>",
    "featureType": "class",
    "class": "hunter",
    "group": "keeper-of-the-balance",
    "subclass": true,
    "gainedAtLevel": 3,
    "gainedAtLevels": [3],
    "selectionCountByLevel": {}
  },
  "effects": [],
  "sort": 0,
  "ownership": {
    "default": 0,
    "h42CcTzyU22SgcaA": 3
  },
  "flags": {},
  "_stats": {
    "compendiumSource": null,
    "duplicateSource": null,
    "exportSource": null,
    "coreVersion": "13.351",
    "systemId": "nimble",
    "systemVersion": "0.8.7",
    "createdTime": 1782932356688,
    "modifiedTime": 1782932430782,
    "lastModifiedBy": "h42CcTzyU22SgcaA"
  },
  "_key": "!items!uQ6maTgZwUx54mau"
}
