{
  "folder": "cFnJp8cGpjVDoYkV",
  "name": "Unified Psyche",
  "type": "feature",
  "_id": "eh06CBeViZEv3Wo6",
  "img": "modules/nimble-nimplus-content/assets/artwork/subclass/psychic-waves.png",
  "system": {
    "macro": "",
    "identifier": "",
    "rules": [],
    "activation": {
      "acquireTargetsFromTemplate": false,
      "cost": {
        "details": "",
        "quantity": 2,
        "type": "action",
        "isReaction": false
      },
      "duration": {
        "details": "",
        "quantity": 1,
        "type": "none"
      },
      "effects": [],
      "showDescription": true,
      "targets": {
        "count": 1,
        "restrictions": "",
        "attackType": "",
        "distance": 1
      },
      "template": {
        "length": 1,
        "radius": 1,
        "shape": "",
        "width": 1
      }
    },
    "description": "<p>(1/encounter) 2 actions: Dispel one of your shadow minions to teleport to the space it was on and make an attack for free (melee/ranged/cantrip). Ignores Rushed Attacks penalty. Repeat this for each of your shadow minions.</p>",
    "featureType": "class",
    "class": "shadowmancer",
    "group": "pact-of-the-id",
    "subclass": true,
    "gainedAtLevel": 15,
    "gainedAtLevels": [15],
    "selectionCountByLevel": {}
  },
  "effects": [],
  "sort": 0,
  "ownership": {
    "default": 0,
    "h42CcTzyU22SgcaA": 3
  },
  "flags": {},
  "_stats": {
    "compendiumSource": null,
    "duplicateSource": null,
    "exportSource": null,
    "coreVersion": "13.351",
    "systemId": "nimble",
    "systemVersion": "0.8.7",
    "createdTime": 1782881408226,
    "modifiedTime": 1782881597494,
    "lastModifiedBy": "h42CcTzyU22SgcaA"
  },
  "_key": "!items!eh06CBeViZEv3Wo6"
}
